example/__init__.py
example/manage-fluent-comments.py
example/manage-fluent-pages.py
example/manage-multilingual.py
example/manage-standalone.py
example/example_fluent_comments/__init__.py
example/example_fluent_comments/settings.py
example/example_fluent_comments/urls.py
example/example_fluent_pages/__init__.py
example/example_fluent_pages/settings.py
example/example_fluent_pages/urls.py
example/example_multilingual/__init__.py
example/example_multilingual/context_processors.py
example/example_multilingual/settings.py
example/example_multilingual/urls.py
example/example_standalone/__init__.py
example/example_standalone/settings.py
example/example_standalone/urls.py
example/theme1/__init__.py
fluent_blogs/__init__.py
fluent_blogs/appsettings.py
fluent_blogs/base_models.py
fluent_blogs/managers.py
fluent_blogs/sitemaps.py
fluent_blogs/urlresolvers.py
fluent_blogs/urls.py
fluent_blogs/admin/__init__.py
fluent_blogs/admin/abstractbase.py
fluent_blogs/admin/entryadmin.py
fluent_blogs/admin/forms.py
fluent_blogs/locale/en/LC_MESSAGES/django.mo
fluent_blogs/locale/en/LC_MESSAGES/django.po
fluent_blogs/locale/nl/LC_MESSAGES/django.mo
fluent_blogs/locale/nl/LC_MESSAGES/django.po
fluent_blogs/management/__init__.py
fluent_blogs/management/commands/__init__.py
fluent_blogs/management/commands/migrate_blog_categories.py
fluent_blogs/migrations/0001_initial.py
fluent_blogs/migrations/0002_intro_allow_null.py
fluent_blogs/migrations/0003_author_on_delete_set_null.py
fluent_blogs/migrations/__init__.py
fluent_blogs/models/__init__.py
fluent_blogs/models/db.py
fluent_blogs/models/managers.py
fluent_blogs/models/query.py
fluent_blogs/pagetypes/__init__.py
fluent_blogs/pagetypes/blogpage/__init__.py
fluent_blogs/pagetypes/blogpage/admin.py
fluent_blogs/pagetypes/blogpage/models.py
fluent_blogs/pagetypes/blogpage/page_type_plugins.py
fluent_blogs/pagetypes/blogpage/migrations/0001_initial.py
fluent_blogs/pagetypes/blogpage/migrations/__init__.py
django_fluent_blogs-3.1.dist-info/AUTHORS
django_fluent_blogs-3.1.dist-info/LICENSE
django_fluent_blogs-3.1.dist-info/METADATA
django_fluent_blogs-3.1.dist-info/WHEEL
django_fluent_blogs-3.1.dist-info/top_level.txt
django_fluent_blogs-3.1.dist-info/RECORD
