Metadata-Version: 2.1
Name: django-fluent-blogs
Version: 3.1
Summary: A blog engine with flexible block contents (based on django-fluent-contents).
Home-page: https://github.com/edoburu/django-fluent-blogs
Download-URL: https://github.com/edoburu/django-fluent-blogs/zipball/master
Author: Diederik van der Boor
Author-email: opensource@edoburu.nl
License: Apache 2.0
Classifier: Development Status :: 5 - Production/Stable
Classifier: Environment :: Web Environment
Classifier: Framework :: Django
Classifier: Intended Audience :: Developers
Classifier: License :: OSI Approved :: Apache Software License
Classifier: Operating System :: OS Independent
Classifier: Programming Language :: Python
Classifier: Programming Language :: Python :: 3.8
Classifier: Programming Language :: Python :: 3.9
Classifier: Programming Language :: Python :: 3.10
Classifier: Framework :: Django
Classifier: Framework :: Django :: 2.2
Classifier: Framework :: Django :: 3.1
Classifier: Framework :: Django :: 3.2
Classifier: Framework :: Django :: 4.0
Classifier: Framework :: Django :: 4.1
Classifier: Framework :: Django :: 4.2
Classifier: Topic :: Internet :: WWW/HTTP
Classifier: Topic :: Internet :: WWW/HTTP :: Dynamic Content
Classifier: Topic :: Software Development :: Libraries :: Application Frameworks
Classifier: Topic :: Software Development :: Libraries :: Python Modules
Requires: Django (>=2.2)
License-File: LICENSE
License-File: AUTHORS
Requires-Dist: django-fluent-contents >=2.0.7
Requires-Dist: django-fluent-utils >=2.0.1
Requires-Dist: django-categories-i18n >=1.1.1
Requires-Dist: django-parler >=2.0.1
Requires-Dist: django-slug-preview >=1.0.4
Requires-Dist: django-tag-parser >=3.2
Provides-Extra: blogpage
Requires-Dist: django-fluent-pages >=2.0.7 ; extra == 'blogpage'
Provides-Extra: taggit
Requires-Dist: taggit ; extra == 'taggit'
Requires-Dist: taggit-autosuggest ; extra == 'taggit'
Provides-Extra: tests
Requires-Dist: django-fluent-pages >=2.0.7 ; extra == 'tests'
Requires-Dist: django-wysiwyg >=0.7.1 ; extra == 'tests'
